{
  "attributes": [
    {
      "id": "System.Notification.BodyTemplate",
      "valueType": "String"
    },
    {
      "id": "System.Notification.BodyText",
      "valueType": "String"
    },
    {
      "id": "System.Notification.SubjectTemplate",
      "valueType": "String"
    },
    {
      "id": "System.Notification.SubjectText",
      "valueType": "String"
    },
    {
      "id": "System.Notification.SentDateTime",
      "valueType": "DateTime"
    },
    {
      "id": "System.Notification.LastTryDateTime",
      "valueType": "DateTime"
    },
    {
      "id": "System.Notification.RecipientAddress",
      "valueType": "String"
    },
    {
      "id": "System.Notification.ErrorText",
      "valueType": "String"
    },
    {
      "id": "System.Notification.Type",
      "valueType": "Int",
      "selectionValues": [
        {
          "key": 1,
          "name": "EMail"
        },
        {
          "key": 2,
          "name": "SMS"
        }
      ]
    },
    {
      "id": "System.Notification.Status",
      "valueType": "Int",
      "selectionValues": [
        {
          "key": 0,
          "name": "Pending"
        },
        {
          "key": 1,
          "name": "Sent"
        },
        {
          "key": 2,
          "name": "Error"
        }
      ]
    }
  ]
}